modelguard/__init__.py
modelguard/benchmark.py
modelguard/components/__init__.py
modelguard/components/benchmark_result.py
modelguard/components/hooked_model_output.py
modelguard/components/monitored_model_output.py
modelguard/config/__init__.py
modelguard/config/config.py
modelguard/enums.py
modelguard/evaluators/__init__.py
modelguard/evaluators/encompassed_monitor_output_evaluator.py
modelguard/evaluators/evaluator.py
modelguard/evaluators/monitor_output_strip_plot_evaluator.py
modelguard/evaluators/ood_probability_confusion_matrix_evaluator.py
modelguard/evaluators/ood_probability_evaluation_metrics_evaluator.py
modelguard/evaluators/relative_id_ood_score_gap_evaluator.py
modelguard/hooked_onnx_model.py
modelguard/model_monitors/__init__.py
modelguard/model_monitors/contained_decoder_reconstruction_monitor.py
modelguard/model_monitors/ensemble_low_res_reconstruction_monitor.py
modelguard/model_monitors/knn_distance_monitor.py
modelguard/model_monitors/low_res_reconstruction_monitor.py
modelguard/model_monitors/model_monitor.py
modelguard/model_monitors/null_monitor.py
modelguard/model_monitors/utils/__init__.py
modelguard/model_monitors/utils/models/__init__.py
modelguard/model_monitors/utils/models/low_res_reconstruction_decoder_model.py
modelguard/model_monitors/utils/trainers/__init__.py
modelguard/model_monitors/utils/trainers/low_res_reconstruction_decoder_trainer.py
modelguard/monitored_model.py
modelguard/post_processors/__init__.py
modelguard/post_processors/max_threshold_post_processor.py
modelguard/post_processors/pass_through_post_processor.py
modelguard/post_processors/post_processor.py
modelguard/py.typed
modelguard/utils/__init__.py
modelguard/utils/general_helpers.py
modelguard/utils/model_monitor_helpers.py
modelguard/utils/sample_helpers.py
modelguard/utils/test_helpers.py
modelguard-0.1.0.dist-info/METADATA
modelguard-0.1.0.dist-info/WHEEL
modelguard-0.1.0.dist-info/RECORD
